webgen/__init__.py
webgen/dom.py
webgen/filegen.py
webgen/wrapper.py
webgen-0.1.0.dist-info/DESCRIPTION.rst
webgen-0.1.0.dist-info/METADATA
webgen-0.1.0.dist-info/RECORD
webgen-0.1.0.dist-info/WHEEL
webgen-0.1.0.dist-info/metadata.json
webgen-0.1.0.dist-info/top_level.txt
