Metadata-Version: 2.0
Name: webgen
Version: 0.1.0
Summary: A Python library for generating and manipulating html, css and javascript files.
Home-page: https://github.com/mikister/webgen
Author: Milan Radojević
Author-email: mikister2012@gmail.com
License: MIT
Provides-Extra: dev
Requires-Dist: check-manifest; extra == 'dev'
Provides-Extra: test
Requires-Dist: coverage; extra == 'test'
